<mxfile host="app.diagrams.net" modified="2020-11-11T18:36:52.481Z" agent="5.0 (Macintosh)" etag="jlF8FICXtg9ENjoVXw_j" version="13.9.6" type="github">
  <diagram id="ZetFakj5iNg6ruvfSLTQ" name="Page-1">
    <mxGraphModel dx="733" dy="466" grid="1" gridSize="10" guides="1" tooltips="1" connect="1" arrows="1" fold="1" page="1" pageScale="1" pageWidth="827" pageHeight="1169" math="0" shadow="0">
      <root>
        <mxCell id="0" />
        <mxCell id="1" parent="0" />
        <mxCell id="qzsLdl5QGXGErAqcGnmE-24" value="" style="rounded=1;whiteSpace=wrap;html=1;align=center;" parent="1" vertex="1">
          <mxGeometry x="40" y="370" width="340" height="170" as="geometry" />
        </mxCell>
        <mxCell id="qzsLdl5QGXGErAqcGnmE-23" value="" style="rounded=1;whiteSpace=wrap;html=1;align=center;" parent="1" vertex="1">
          <mxGeometry x="20" y="30" width="720" height="320" as="geometry" />
        </mxCell>
        <mxCell id="4jmMZtkB6j6rvl_votOX-8" style="edgeStyle=orthogonalEdgeStyle;rounded=0;orthogonalLoop=1;jettySize=auto;html=1;entryX=0.175;entryY=0.5;entryDx=0;entryDy=0;entryPerimeter=0;" parent="1" source="4jmMZtkB6j6rvl_votOX-1" target="4jmMZtkB6j6rvl_votOX-2" edge="1">
          <mxGeometry relative="1" as="geometry" />
        </mxCell>
        <mxCell id="4jmMZtkB6j6rvl_votOX-12" style="edgeStyle=orthogonalEdgeStyle;rounded=0;orthogonalLoop=1;jettySize=auto;html=1;entryX=0.175;entryY=0.5;entryDx=0;entryDy=0;entryPerimeter=0;curved=1;dashed=1;" parent="1" source="4jmMZtkB6j6rvl_votOX-1" target="4jmMZtkB6j6rvl_votOX-6" edge="1">
          <mxGeometry relative="1" as="geometry">
            <Array as="points">
              <mxPoint x="160" y="99" />
              <mxPoint x="160" y="289" />
            </Array>
          </mxGeometry>
        </mxCell>
        <mxCell id="REPX3PMfL959SOM3CvPV-1" style="edgeStyle=orthogonalEdgeStyle;rounded=0;orthogonalLoop=1;jettySize=auto;html=1;entryX=0.5;entryY=0.16;entryDx=0;entryDy=0;entryPerimeter=0;curved=1;dashed=1;dashPattern=1 2;strokeColor=#FF33FF;" parent="1" source="4jmMZtkB6j6rvl_votOX-1" target="qzsLdl5QGXGErAqcGnmE-12" edge="1">
          <mxGeometry relative="1" as="geometry">
            <Array as="points">
              <mxPoint x="130" y="99" />
              <mxPoint x="130" y="240" />
            </Array>
          </mxGeometry>
        </mxCell>
        <mxCell id="4jmMZtkB6j6rvl_votOX-1" value="Verse One" style="html=1;fillColor=#5184F3;strokeColor=none;verticalAlign=bottom;labelPosition=center;verticalLabelPosition=top;align=center;spacingTop=-6;fontSize=11;fontStyle=1;shape=mxgraph.gcp2.hexIcon;prIcon=cloud_functions;" parent="1" vertex="1">
          <mxGeometry x="40" y="70" width="66" height="58.5" as="geometry" />
        </mxCell>
        <mxCell id="4jmMZtkB6j6rvl_votOX-9" style="edgeStyle=orthogonalEdgeStyle;rounded=0;orthogonalLoop=1;jettySize=auto;html=1;entryX=0.175;entryY=0.5;entryDx=0;entryDy=0;entryPerimeter=0;" parent="1" source="4jmMZtkB6j6rvl_votOX-2" target="4jmMZtkB6j6rvl_votOX-3" edge="1">
          <mxGeometry relative="1" as="geometry" />
        </mxCell>
        <mxCell id="4jmMZtkB6j6rvl_votOX-2" value="Cloud&#xa;Pub/Sub" style="html=1;fillColor=#5184F3;strokeColor=none;verticalAlign=top;labelPosition=center;verticalLabelPosition=bottom;align=center;spacingTop=-6;fontSize=11;fontStyle=1;fontColor=#999999;shape=mxgraph.gcp2.hexIcon;prIcon=cloud_pubsub" parent="1" vertex="1">
          <mxGeometry x="190" y="70" width="66" height="58.5" as="geometry" />
        </mxCell>
        <mxCell id="4jmMZtkB6j6rvl_votOX-10" style="edgeStyle=orthogonalEdgeStyle;rounded=0;orthogonalLoop=1;jettySize=auto;html=1;entryX=0.175;entryY=0.5;entryDx=0;entryDy=0;entryPerimeter=0;" parent="1" source="4jmMZtkB6j6rvl_votOX-3" target="4jmMZtkB6j6rvl_votOX-4" edge="1">
          <mxGeometry relative="1" as="geometry" />
        </mxCell>
        <mxCell id="4jmMZtkB6j6rvl_votOX-19" style="edgeStyle=orthogonalEdgeStyle;curved=1;rounded=0;orthogonalLoop=1;jettySize=auto;html=1;entryX=0.5;entryY=0.16;entryDx=0;entryDy=0;entryPerimeter=0;fontColor=#000000;dashed=1;" parent="1" source="4jmMZtkB6j6rvl_votOX-3" target="4jmMZtkB6j6rvl_votOX-6" edge="1">
          <mxGeometry relative="1" as="geometry" />
        </mxCell>
        <mxCell id="REPX3PMfL959SOM3CvPV-2" style="edgeStyle=orthogonalEdgeStyle;curved=1;rounded=0;orthogonalLoop=1;jettySize=auto;html=1;entryX=0.5;entryY=0.16;entryDx=0;entryDy=0;entryPerimeter=0;dashed=1;dashPattern=1 2;strokeColor=#FF33FF;exitX=0.5;exitY=0.84;exitDx=0;exitDy=0;exitPerimeter=0;" parent="1" source="4jmMZtkB6j6rvl_votOX-3" target="qzsLdl5QGXGErAqcGnmE-12" edge="1">
          <mxGeometry relative="1" as="geometry">
            <Array as="points">
              <mxPoint x="373" y="180" />
              <mxPoint x="173" y="180" />
            </Array>
          </mxGeometry>
        </mxCell>
        <mxCell id="4jmMZtkB6j6rvl_votOX-3" value="Verse Two" style="html=1;fillColor=#5184F3;strokeColor=none;verticalAlign=bottom;labelPosition=center;verticalLabelPosition=top;align=center;spacingTop=-6;fontSize=11;fontStyle=1;shape=mxgraph.gcp2.hexIcon;prIcon=cloud_functions;" parent="1" vertex="1">
          <mxGeometry x="340" y="70" width="66" height="58.5" as="geometry" />
        </mxCell>
        <mxCell id="4jmMZtkB6j6rvl_votOX-11" style="edgeStyle=orthogonalEdgeStyle;rounded=0;orthogonalLoop=1;jettySize=auto;html=1;entryX=0.175;entryY=0.5;entryDx=0;entryDy=0;entryPerimeter=0;" parent="1" source="4jmMZtkB6j6rvl_votOX-4" target="4jmMZtkB6j6rvl_votOX-5" edge="1">
          <mxGeometry relative="1" as="geometry" />
        </mxCell>
        <mxCell id="4jmMZtkB6j6rvl_votOX-4" value="Cloud&#xa;Pub/Sub" style="html=1;fillColor=#5184F3;strokeColor=none;verticalAlign=top;labelPosition=center;verticalLabelPosition=bottom;align=center;spacingTop=-6;fontSize=11;fontStyle=1;fontColor=#999999;shape=mxgraph.gcp2.hexIcon;prIcon=cloud_pubsub" parent="1" vertex="1">
          <mxGeometry x="490" y="70" width="66" height="58.5" as="geometry" />
        </mxCell>
        <mxCell id="4jmMZtkB6j6rvl_votOX-20" style="edgeStyle=orthogonalEdgeStyle;curved=1;rounded=0;orthogonalLoop=1;jettySize=auto;html=1;entryX=0.825;entryY=0.5;entryDx=0;entryDy=0;entryPerimeter=0;fontColor=#000000;dashed=1;" parent="1" source="4jmMZtkB6j6rvl_votOX-5" target="4jmMZtkB6j6rvl_votOX-6" edge="1">
          <mxGeometry relative="1" as="geometry">
            <Array as="points">
              <mxPoint x="600" y="99" />
              <mxPoint x="600" y="289" />
            </Array>
          </mxGeometry>
        </mxCell>
        <mxCell id="REPX3PMfL959SOM3CvPV-4" style="edgeStyle=orthogonalEdgeStyle;curved=1;rounded=0;orthogonalLoop=1;jettySize=auto;html=1;entryX=0.5;entryY=0.308;entryDx=0;entryDy=0;entryPerimeter=0;dashed=1;dashPattern=1 2;strokeColor=#FF33FF;exitX=0.5;exitY=0.84;exitDx=0;exitDy=0;exitPerimeter=0;" parent="1" source="4jmMZtkB6j6rvl_votOX-5" target="qzsLdl5QGXGErAqcGnmE-12" edge="1">
          <mxGeometry relative="1" as="geometry">
            <Array as="points">
              <mxPoint x="673" y="210" />
              <mxPoint x="173" y="210" />
            </Array>
          </mxGeometry>
        </mxCell>
        <mxCell id="4jmMZtkB6j6rvl_votOX-5" value="Verse Three" style="html=1;fillColor=#5184F3;strokeColor=none;verticalAlign=bottom;labelPosition=center;verticalLabelPosition=top;align=center;spacingTop=-6;fontSize=11;fontStyle=1;shape=mxgraph.gcp2.hexIcon;prIcon=cloud_functions;" parent="1" vertex="1">
          <mxGeometry x="640" y="70" width="66" height="58.5" as="geometry" />
        </mxCell>
        <mxCell id="REPX3PMfL959SOM3CvPV-3" style="edgeStyle=orthogonalEdgeStyle;curved=1;rounded=0;orthogonalLoop=1;jettySize=auto;html=1;entryX=0.5;entryY=0.16;entryDx=0;entryDy=0;entryPerimeter=0;exitX=0.25;exitY=0.67;exitDx=0;exitDy=0;exitPerimeter=0;dashed=1;dashPattern=1 2;strokeColor=#FF33FF;" parent="1" source="4jmMZtkB6j6rvl_votOX-6" target="qzsLdl5QGXGErAqcGnmE-12" edge="1">
          <mxGeometry relative="1" as="geometry" />
        </mxCell>
        <mxCell id="4jmMZtkB6j6rvl_votOX-6" value="Chorus" style="html=1;fillColor=#5184F3;strokeColor=none;verticalAlign=top;labelPosition=center;verticalLabelPosition=bottom;align=center;spacingTop=-6;fontSize=11;fontStyle=1;shape=mxgraph.gcp2.hexIcon;prIcon=cloud_functions;" parent="1" vertex="1">
          <mxGeometry x="340" y="260" width="66" height="58.5" as="geometry" />
        </mxCell>
        <mxCell id="REPX3PMfL959SOM3CvPV-5" style="edgeStyle=orthogonalEdgeStyle;curved=1;rounded=0;orthogonalLoop=1;jettySize=auto;html=1;entryX=0.5;entryY=0.16;entryDx=0;entryDy=0;entryPerimeter=0;dashed=1;dashPattern=1 2;strokeColor=#FF33FF;exitX=0.5;exitY=0.84;exitDx=0;exitDy=0;exitPerimeter=0;" parent="1" source="qzsLdl5QGXGErAqcGnmE-12" target="qzsLdl5QGXGErAqcGnmE-18" edge="1">
          <mxGeometry relative="1" as="geometry">
            <Array as="points">
              <mxPoint x="173" y="420" />
              <mxPoint x="283" y="420" />
            </Array>
          </mxGeometry>
        </mxCell>
        <mxCell id="qzsLdl5QGXGErAqcGnmE-12" value="&lt;div&gt;vpc connector&lt;/div&gt;" style="html=1;fillColor=#5184F3;strokeColor=none;verticalAlign=middle;labelPosition=left;verticalLabelPosition=middle;align=right;spacingTop=-6;fontSize=11;fontStyle=1;fontColor=#999999;shape=mxgraph.gcp2.hexIcon;prIcon=dedicated_interconnect" parent="1" vertex="1">
          <mxGeometry x="140" y="333" width="66" height="58.5" as="geometry" />
        </mxCell>
        <mxCell id="qzsLdl5QGXGErAqcGnmE-13" value="Virtual&#xa;Private Cloud" style="html=1;fillColor=#5184F3;strokeColor=none;verticalAlign=middle;labelPosition=left;verticalLabelPosition=middle;align=right;spacingTop=-6;fontSize=11;fontStyle=1;fontColor=#999999;shape=mxgraph.gcp2.hexIcon;prIcon=virtual_private_cloud" parent="1" vertex="1">
          <mxGeometry x="314" y="370" width="66" height="58.5" as="geometry" />
        </mxCell>
        <mxCell id="qzsLdl5QGXGErAqcGnmE-17" value="Cloud&#xa;Firewall Rules" style="html=1;fillColor=#5184F3;strokeColor=none;verticalAlign=top;labelPosition=center;verticalLabelPosition=bottom;align=center;spacingTop=-6;fontSize=11;fontStyle=1;fontColor=#999999;shape=mxgraph.gcp2.hexIcon;prIcon=cloud_firewall_rules" parent="1" vertex="1">
          <mxGeometry x="60" y="380" width="66" height="58.5" as="geometry" />
        </mxCell>
        <mxCell id="qzsLdl5QGXGErAqcGnmE-18" value="&lt;div&gt;Jaeger Host&lt;/div&gt;" style="html=1;fillColor=#5184F3;strokeColor=none;verticalAlign=top;labelPosition=center;verticalLabelPosition=bottom;align=center;spacingTop=-6;fontSize=11;fontStyle=1;fontColor=#999999;shape=mxgraph.gcp2.hexIcon;prIcon=compute_engine" parent="1" vertex="1">
          <mxGeometry x="250" y="461.13" width="66" height="58.5" as="geometry" />
        </mxCell>
        <mxCell id="REPX3PMfL959SOM3CvPV-6" style="rounded=0;orthogonalLoop=1;jettySize=auto;html=1;dashed=1;dashPattern=1 1;" parent="1" source="qzsLdl5QGXGErAqcGnmE-19" edge="1">
          <mxGeometry relative="1" as="geometry">
            <mxPoint x="250" y="491" as="targetPoint" />
          </mxGeometry>
        </mxCell>
        <mxCell id="qzsLdl5QGXGErAqcGnmE-19" value="Template" style="rounded=0;whiteSpace=wrap;html=1;align=center;" parent="1" vertex="1">
          <mxGeometry x="142" y="464.63" width="64" height="51.5" as="geometry" />
        </mxCell>
      </root>
    </mxGraphModel>
  </diagram>
</mxfile>
